{
  "name": "Sell Cattle",
  "created": "2022-06-21T15:51:33.9820663+02:00",
  "pages": [
    {
      "fieldSets": [
        {
          "caption": null,
          "sortOrder": 0,
          "id": "00000000-0000-0000-0000-000000000000",
          "page": "00000000-0000-0000-0000-000000000000",
          "containers": [
            {
              "caption": null,
              "width": 12,
              "fields": [
                {
                  "caption": "Name & Surname/Naam en Van",
                  "tooltip": null,
                  "placeholder": null,
                  "cssClass": null,
                  "alias": "name",
                  "id": "f6718dda-0e45-48f9-bf8f-ecfe8a500a9e",
                  "fieldTypeId": "3f92e01b-29e2-4a30-bf33-9df5580ed52c",
                  "prevalueSourceId": "00000000-0000-0000-0000-000000000000",
                  "dataSourceFieldKey": null,
                  "containsSensitiveData": false,
                  "mandatory": true,
                  "regex": null,
                  "requiredErrorMessage": null,
                  "invalidErrorMessage": null,
                  "condition": {
                    "id": "00000000-0000-0000-0000-000000000000",
                    "enabled": false,
                    "actionType": "Show",
                    "logicType": "All",
                    "rules": []
                  },
                  "settings": {
                    "DefaultValue": "",
                    "Placeholder": ""
                  },
                  "preValues": [],
                  "allowedUploadTypes": null,
                  "allowMultipleFileUploads": true
                },
                {
                  "caption": "Email/Epos",
                  "tooltip": null,
                  "placeholder": null,
                  "cssClass": null,
                  "alias": "email",
                  "id": "c9204231-7756-4e10-cb50-60870fb4bb73",
                  "fieldTypeId": "3f92e01b-29e2-4a30-bf33-9df5580ed52c",
                  "prevalueSourceId": "00000000-0000-0000-0000-000000000000",
                  "dataSourceFieldKey": null,
                  "containsSensitiveData": false,
                  "mandatory": true,
                  "regex": null,
                  "requiredErrorMessage": null,
                  "invalidErrorMessage": null,
                  "condition": {
                    "id": "00000000-0000-0000-0000-000000000000",
                    "enabled": false,
                    "actionType": "Show",
                    "logicType": "All",
                    "rules": []
                  },
                  "settings": {
                    "DefaultValue": "",
                    "Placeholder": ""
                  },
                  "preValues": [],
                  "allowedUploadTypes": null,
                  "allowMultipleFileUploads": true
                },
                {
                  "caption": "Address/Adres",
                  "tooltip": null,
                  "placeholder": null,
                  "cssClass": null,
                  "alias": "message",
                  "id": "d69e4ea5-4957-4b27-f572-cae872e2dc75",
                  "fieldTypeId": "023f09ac-1445-4bcb-b8fa-ab49f33bd046",
                  "prevalueSourceId": "00000000-0000-0000-0000-000000000000",
                  "dataSourceFieldKey": null,
                  "containsSensitiveData": false,
                  "mandatory": true,
                  "regex": null,
                  "requiredErrorMessage": null,
                  "invalidErrorMessage": null,
                  "condition": {
                    "id": "00000000-0000-0000-0000-000000000000",
                    "enabled": false,
                    "actionType": "Show",
                    "logicType": "All",
                    "rules": []
                  },
                  "settings": {
                    "DefaultValue": "",
                    "Placeholder": "",
                    "NumberOfRows": "4"
                  },
                  "preValues": [],
                  "allowedUploadTypes": null,
                  "allowMultipleFileUploads": true
                },
                {
                  "caption": "Business Name/Besigheidsnaam",
                  "tooltip": null,
                  "placeholder": null,
                  "cssClass": null,
                  "alias": "businessNameBesigheidsnaam",
                  "id": "b145f8c9-6ab0-4748-9616-1b85784e948d",
                  "fieldTypeId": "023f09ac-1445-4bcb-b8fa-ab49f33bd046",
                  "prevalueSourceId": "00000000-0000-0000-0000-000000000000",
                  "dataSourceFieldKey": null,
                  "containsSensitiveData": false,
                  "mandatory": true,
                  "regex": null,
                  "requiredErrorMessage": null,
                  "invalidErrorMessage": null,
                  "condition": {
                    "id": "00000000-0000-0000-0000-000000000000",
                    "enabled": false,
                    "actionType": "Show",
                    "logicType": "All",
                    "rules": []
                  },
                  "settings": {
                    "NumberOfRows": "1",
                    "DefaultValue": "",
                    "Placeholder": ""
                  },
                  "preValues": [],
                  "allowedUploadTypes": null,
                  "allowMultipleFileUploads": true
                },
                {
                  "caption": "Mobile/Selfoon",
                  "tooltip": null,
                  "placeholder": null,
                  "cssClass": null,
                  "alias": "mobileSelfoon",
                  "id": "fbf3456e-136d-48b5-ec7e-0fd27ad270ac",
                  "fieldTypeId": "3f92e01b-29e2-4a30-bf33-9df5580ed52c",
                  "prevalueSourceId": "00000000-0000-0000-0000-000000000000",
                  "dataSourceFieldKey": null,
                  "containsSensitiveData": false,
                  "mandatory": true,
                  "regex": null,
                  "requiredErrorMessage": null,
                  "invalidErrorMessage": null,
                  "condition": {
                    "id": "00000000-0000-0000-0000-000000000000",
                    "enabled": false,
                    "actionType": "Show",
                    "logicType": "All",
                    "rules": []
                  },
                  "settings": {
                    "DefaultValue": "",
                    "Placeholder": ""
                  },
                  "preValues": [],
                  "allowedUploadTypes": null,
                  "allowMultipleFileUploads": true
                },
                {
                  "caption": "Amount of Cattle for Sale",
                  "tooltip": null,
                  "placeholder": null,
                  "cssClass": null,
                  "alias": "amountOfCattleForSale",
                  "id": "8b350014-8099-4901-a579-37888146b5b2",
                  "fieldTypeId": "3f92e01b-29e2-4a30-bf33-9df5580ed52c",
                  "prevalueSourceId": "00000000-0000-0000-0000-000000000000",
                  "dataSourceFieldKey": null,
                  "containsSensitiveData": false,
                  "mandatory": false,
                  "regex": null,
                  "requiredErrorMessage": null,
                  "invalidErrorMessage": null,
                  "condition": {
                    "id": "00000000-0000-0000-0000-000000000000",
                    "enabled": false,
                    "actionType": "Show",
                    "logicType": "All",
                    "rules": []
                  },
                  "settings": {},
                  "preValues": [],
                  "allowedUploadTypes": null,
                  "allowMultipleFileUploads": true
                },
                {
                  "caption": "What Country are you From",
                  "tooltip": null,
                  "placeholder": null,
                  "cssClass": null,
                  "alias": "whatCountryAreYouFrom",
                  "id": "f80af13d-dc3c-4127-f411-491cd4760852",
                  "fieldTypeId": "0dd29d42-a6a5-11de-a2f2-222256d89593",
                  "prevalueSourceId": "17fc9103-be80-4a39-92ba-9ad1375944b6",
                  "dataSourceFieldKey": null,
                  "containsSensitiveData": false,
                  "mandatory": true,
                  "regex": null,
                  "requiredErrorMessage": null,
                  "invalidErrorMessage": null,
                  "condition": {
                    "id": "00000000-0000-0000-0000-000000000000",
                    "enabled": false,
                    "actionType": "Show",
                    "logicType": "All",
                    "rules": []
                  },
                  "settings": {
                    "DefaultValue": "",
                    "AllowMultipleSelections": ""
                  },
                  "preValues": [],
                  "allowedUploadTypes": null,
                  "allowMultipleFileUploads": true
                },
                {
                  "caption": "Language",
                  "tooltip": null,
                  "placeholder": null,
                  "cssClass": null,
                  "alias": "language",
                  "id": "2fbda066-3464-4eb1-9646-bcfbea4eb60f",
                  "fieldTypeId": "0dd29d42-a6a5-11de-a2f2-222256d89593",
                  "prevalueSourceId": "00000000-0000-0000-0000-000000000000",
                  "dataSourceFieldKey": null,
                  "containsSensitiveData": false,
                  "mandatory": true,
                  "regex": null,
                  "requiredErrorMessage": null,
                  "invalidErrorMessage": null,
                  "condition": {
                    "id": "00000000-0000-0000-0000-000000000000",
                    "enabled": false,
                    "actionType": "Show",
                    "logicType": "All",
                    "rules": []
                  },
                  "settings": {
                    "DefaultValue": "",
                    "AllowMultipleSelections": ""
                  },
                  "preValues": [
                    "English",
                    "Afrikaans"
                  ],
                  "allowedUploadTypes": null,
                  "allowMultipleFileUploads": true
                },
                {
                  "caption": "Consent for storing submitted data",
                  "tooltip": null,
                  "placeholder": null,
                  "cssClass": null,
                  "alias": "dataConsent",
                  "id": "496d186b-b77c-4183-b9bc-a08901f5237f",
                  "fieldTypeId": "a72c9df9-3847-47cf-afb8-b86773fd12cd",
                  "prevalueSourceId": "00000000-0000-0000-0000-000000000000",
                  "dataSourceFieldKey": null,
                  "containsSensitiveData": false,
                  "mandatory": true,
                  "regex": null,
                  "requiredErrorMessage": "Consent is required to store and process the data in this form.",
                  "invalidErrorMessage": null,
                  "condition": null,
                  "settings": {
                    "AcceptCopy": "Yes, I give permission to store and process my data"
                  },
                  "preValues": null,
                  "allowedUploadTypes": null,
                  "allowMultipleFileUploads": true
                }
              ]
            }
          ],
          "condition": {
            "id": "00000000-0000-0000-0000-000000000000",
            "enabled": false,
            "actionType": "Show",
            "logicType": "All",
            "rules": []
          }
        }
      ],
      "caption": "Sell Cattle",
      "sortOrder": 0,
      "id": "00000000-0000-0000-0000-000000000000",
      "form": "00000000-0000-0000-0000-000000000000"
    }
  ],
  "id": "a5f5436f-5880-4624-8461-57d260fa20bd",
  "fieldIndicationType": "MarkMandatoryFields",
  "indicator": "*",
  "showValidationSummary": false,
  "hideFieldValidation": false,
  "requiredErrorMessage": "Please provide a value for {0}",
  "invalidErrorMessage": "Please provide a valid value for {0}",
  "messageOnSubmit": "Thank you",
  "goToPageOnSubmit": 3937,
  "xPathOnSubmit": null,
  "manualApproval": false,
  "storeRecordsLocally": true,
  "cssClass": "needs-validation",
  "disableDefaultStylesheet": false,
  "useClientDependency": false,
  "workflows": [
    "e34060f1-ed80-4cc8-8865-ce873f535779"
  ],
  "datasource": null,
  "submitLabel": "Submit",
  "nextLabel": "Next",
  "prevLabel": "Prev"
}